pyvelox/legacy.cpython-310-darwin.so
pyvelox/libvelox.dylib
pyvelox/plan_builder.cpython-310-darwin.so
pyvelox/__init__.py
pyvelox/type.cpython-310-darwin.so
pyvelox/vector.cpython-310-darwin.so
pyvelox/arrow.cpython-310-darwin.so
pyvelox/runner.cpython-310-darwin.so
pyvelox/file.cpython-310-darwin.so
pyvelox/utils/__init__.py
pyvelox/utils/run_queries.py
pyvelox/utils/data_generator.py
pyvelox/.dylibs/libsodium.26.dylib
pyvelox/.dylibs/libboost_thread.dylib
pyvelox/.dylibs/liblz4.1.10.0.dylib
pyvelox/.dylibs/libsnappy.1.2.1.dylib
pyvelox/.dylibs/liblzo2.2.dylib
pyvelox/.dylibs/libssl.3.dylib
pyvelox/.dylibs/libcrypto.3.dylib
pyvelox/.dylibs/libgflags.2.2.2.dylib
pyvelox/.dylibs/libboost_regex.dylib
pyvelox/.dylibs/libboost_program_options.dylib
pyvelox/.dylibs/libevent-2.1.7.dylib
pyvelox/.dylibs/libglog.0.6.0.dylib
pyvelox/.dylibs/libboost_filesystem.dylib
pyvelox/.dylibs/libboost_atomic.dylib
pyvelox/.dylibs/libboost_system.dylib
pyvelox/.dylibs/libzstd.1.5.7.dylib
pyvelox/.dylibs/libboost_context.dylib
pyvelox-0.2.0.dist-info/RECORD
pyvelox-0.2.0.dist-info/WHEEL
pyvelox-0.2.0.dist-info/METADATA
pyvelox-0.2.0.dist-info/licenses/LICENSE
pyvelox-0.2.0.dist-info/licenses/NOTICE.txt
