Metadata-Version: 2.4
Name: PyVelox
Version: 0.2.0
Summary: Python bindings and extensions for Velox
Author-Email: Meta <velox@fb.com>
Maintainer-Email: Meta <velox@fb.com>
License-Expression: Apache-2.0
Classifier: Intended Audience :: Developers
Classifier: Intended Audience :: Science/Research
Classifier: Operating System :: POSIX :: Linux
Classifier: Programming Language :: C++
Classifier: Programming Language :: Python :: 3.9
Classifier: Programming Language :: Python :: 3.10
Classifier: Programming Language :: Python :: 3.11
Classifier: Programming Language :: Python :: 3.12
Classifier: Programming Language :: Python :: Implementation :: CPython
Project-URL: homepage, https://github.com/facebookincubator/velox
Requires-Python: >=3.9
Requires-Dist: pyarrow
